matrops/__init__.py
matrops/__main__.py
matrops/exceptions.py
matrops/matrix/Matrix.py
matrops/matrix/Operations.py
matrops/matrix/__init__.py
matrops/vector/Operations.py
matrops/vector/Vector.py
matrops/vector/__init__.py
matrops-0.1.2.dist-info/LICENSE
matrops-0.1.2.dist-info/METADATA
matrops-0.1.2.dist-info/WHEEL
matrops-0.1.2.dist-info/top_level.txt
matrops-0.1.2.dist-info/RECORD
