Metadata-Version: 2.1
Name: matrops
Version: 0.1.2
Summary: Package for matrix and vector operations in python
Home-page: https://github.com/Jolumine/matrops
Author: Leonard Becker
License: MIT
Keywords: matrix,vector,operations,python,package
Requires-Python: <4,>=3.7
License-File: LICENSE
